flask_ldap3_login/__init__.py
flask_ldap3_login/forms.py
flask_ldap3_login-1.0.2.dist-info/LICENSE
flask_ldap3_login-1.0.2.dist-info/METADATA
flask_ldap3_login-1.0.2.dist-info/WHEEL
flask_ldap3_login-1.0.2.dist-info/top_level.txt
flask_ldap3_login-1.0.2.dist-info/RECORD
