Metadata-Version: 2.1
Name: flask-ldap3-login
Version: 1.0.2
Summary: LDAP Support for Flask
Author-email: Nick Whyte <nick@nickwhyte.com>
License: MIT
Project-URL: Homepage, https://github.com/nickw444/flask-ldap3-login
Classifier: Environment :: Web Environment
Classifier: Framework :: Flask
Classifier: Intended Audience :: Developers
Classifier: Programming Language :: Python
Classifier: Programming Language :: Python :: 3
Classifier: Programming Language :: Python :: 3 :: Only
Classifier: Programming Language :: Python :: 3.5
Classifier: Programming Language :: Python :: 3.6
Classifier: Programming Language :: Python :: 3.7
Requires-Python: >=3.5
License-File: LICENSE
Requires-Dist: Flask
Requires-Dist: Flask-wtf
Requires-Dist: WTForms>=1.0.2
Requires-Dist: ldap3>=2.0.7
